pyunit/__init__.py
pyunit/__init__.pyi
pyunit/_about.py
pyunit/math.py
pyunit/math.pyi
pyunit/_internal/__init__.py
pyunit/_internal/arithmetics.py
pyunit/_internal/core.py
pyunit/_internal/core.pyi
pyunit/_internal/generators.py
pyunit/_internal/generators.pyi
pyunit_neo-1.0.2.dist-info/licenses/LICENSE
pyunit_neo-1.0.2.dist-info/METADATA
pyunit_neo-1.0.2.dist-info/WHEEL
pyunit_neo-1.0.2.dist-info/top_level.txt
pyunit_neo-1.0.2.dist-info/RECORD
