Metadata-Version: 2.4
Name: PyUnit-Neo
Version: 1.0.2
Summary: Tools for readable unit types, geometry, and trigonometric utilities.
Home-page: https://github.com/NeoZett-School/PyUnit
Author: Neo Zetterberg
Author-email: Neo Zetterberg <your-email@example.com>
License: MIT
Project-URL: Bug-Tracker, https://github.com/NeoZett-School/PyUnit/issues
Project-URL: Documentation, https://github.com/NeoZett-School/PyUnit#readme
Project-URL: Source, https://github.com/NeoZett-School/PyUnit
Keywords: units,measurement,geometry,trigonometry,math
Classifier: Development Status :: 3 - Alpha
Classifier: Intended Audience :: Developers
Classifier: License :: OSI Approved :: MIT License
Classifier: Programming Language :: Python :: 3
Classifier: Programming Language :: Python :: 3.10
Classifier: Operating System :: Microsoft :: Windows
Classifier: Topic :: Software Development :: Libraries
Requires-Python: >=3.10
License-File: LICENSE
Dynamic: license-file
